polyfemos/CONTRIBUTORS.txt
polyfemos/LICENCE.txt
polyfemos/VERSION.txt
polyfemos/__init__.py
polyfemos/almanac/__init__.py
polyfemos/almanac/ordinal.py
polyfemos/almanac/timer.py
polyfemos/almanac/utils.py
polyfemos/back/__init__.py
polyfemos/back/filewriter.py
polyfemos/back/interpreter.py
polyfemos/back/main.py
polyfemos/back/parameter.py
polyfemos/back/station.py
polyfemos/back/seismic/__init__.py
polyfemos/back/seismic/edlogreader.py
polyfemos/back/seismic/lumberjack.py
polyfemos/back/seismic/scanner.py
polyfemos/data/__init__.py
polyfemos/data/outlierremover.py
polyfemos/data/statistics.py
polyfemos/data/utils.py
polyfemos/front/__init__.py
polyfemos/front/alertreader.py
polyfemos/front/colors.py
polyfemos/front/flask_config.py
polyfemos/front/forms.py
polyfemos/front/main.py
polyfemos/front/request.py
polyfemos/front/trafficmonitor.py
polyfemos/front/userdef.py
polyfemos/front/sohplot/__init__.py
polyfemos/front/sohplot/datacontainer.py
polyfemos/front/sohplot/offsets.py
polyfemos/front/sohplot/outfilefields.py
polyfemos/front/sohplot/sohplot.py
polyfemos/front/static/datepicker.js
polyfemos/front/static/ou_logo_en.svg
polyfemos/front/static/polyfemos_favicon.ico
polyfemos/front/static/polyfemos_favicon_32.ico
polyfemos/front/static/sorttable.js
polyfemos/front/static/styles.css
polyfemos/front/templates/alertheat.htm
polyfemos/front/templates/base.htm
polyfemos/front/templates/datacoveragebrowser.htm
polyfemos/front/templates/datacoverageimage.htm
polyfemos/front/templates/datepicker.htm
polyfemos/front/templates/home.htm
polyfemos/front/templates/index.htm
polyfemos/front/templates/message.htm
polyfemos/front/templates/plotbrowser.htm
polyfemos/front/templates/sohmap.htm
polyfemos/front/templates/sohtable.htm
polyfemos/front/templates/summary.htm
polyfemos/parser/__init__.py
polyfemos/parser/filepathparser.py
polyfemos/parser/functionparser.py
polyfemos/parser/resources.py
polyfemos/parser/typeoperator.py
polyfemos/scripts/__init__.py
polyfemos-0.3.33.dist-info/METADATA
polyfemos-0.3.33.dist-info/WHEEL
polyfemos-0.3.33.dist-info/entry_points.txt
polyfemos-0.3.33.dist-info/top_level.txt
polyfemos-0.3.33.dist-info/RECORD
